LICENSE
MANIFEST.in
README.rst
pyproject.toml
setup.cfg
setup.py
versioneer.py
hector/LICENSE.md
hector/README.md
hector/inst/include/avisitor.hpp
hector/inst/include/bc_component.hpp
hector/inst/include/carbon-cycle-model.hpp
hector/inst/include/carbon-cycle-solver.hpp
hector/inst/include/ch4_component.hpp
hector/inst/include/component_data.hpp
hector/inst/include/component_names.hpp
hector/inst/include/core.hpp
hector/inst/include/csv_outputstream_visitor.hpp
hector/inst/include/csv_table_reader.hpp
hector/inst/include/csv_tracking_visitor.hpp
hector/inst/include/dependency_finder.hpp
hector/inst/include/dummy_model_component.hpp
hector/inst/include/fluxpool.hpp
hector/inst/include/forcing_component.hpp
hector/inst/include/h_exception.hpp
hector/inst/include/h_interpolator.hpp
hector/inst/include/h_reader.hpp
hector/inst/include/h_util.hpp
hector/inst/include/halocarbon_component.hpp
hector/inst/include/hector.hpp
hector/inst/include/imodel_component.hpp
hector/inst/include/ini_to_core_reader.hpp
hector/inst/include/ivisitable.hpp
hector/inst/include/logger.hpp
hector/inst/include/message_data.hpp
hector/inst/include/n2o_component.hpp
hector/inst/include/nh3_component.hpp
hector/inst/include/o3_component.hpp
hector/inst/include/oc_component.hpp
hector/inst/include/ocean_component.hpp
hector/inst/include/ocean_csys.hpp
hector/inst/include/oceanbox.hpp
hector/inst/include/oh_component.hpp
hector/inst/include/simpleNbox.hpp
hector/inst/include/slr_component.hpp
hector/inst/include/so2_component.hpp
hector/inst/include/temperature_component.hpp
hector/inst/include/tseries.hpp
hector/inst/include/tvector.hpp
hector/inst/include/unitval.hpp
hector/src/bc_component.cpp
hector/src/carbon-cycle-model.cpp
hector/src/carbon-cycle-solver.cpp
hector/src/ch4_component.cpp
hector/src/core.cpp
hector/src/csv_outputstream_visitor.cpp
hector/src/csv_table_reader.cpp
hector/src/csv_tracking_visitor.cpp
hector/src/dependency_finder.cpp
hector/src/dummy_model_component.cpp
pyhector.egg-info/PKG-INFO
pyhector.egg-info/SOURCES.txt
pyhector.egg-info/dependency_links.txt
pyhector.egg-info/not-zip-safe
pyhector.egg-info/requires.txt
pyhector.egg-info/top_level.txt
