Metadata-Version: 2.1
Name: pyhector
Version: 3.2.0.0
Summary: Python wrapper for the Hector simple climate model
Home-page: https://github.com/openclimatedata/pyhector
Author: Sven Willner, Robert Gieseke
Author-email: sven.willner@gmail.com, rob.g@web.de
License: GNU Affero General Public License v3
Keywords: climate model climate change
Platform: any
Classifier: Development Status :: 4 - Beta
Classifier: Intended Audience :: Developers
Classifier: Operating System :: OS Independent
Classifier: Programming Language :: Python :: 3.7
Classifier: Programming Language :: Python :: 3.8
Classifier: Programming Language :: Python :: 3.9
Provides-Extra: docs
Provides-Extra: tests
License-File: LICENSE
